README.md
setup.py
helputils/__init__.py
helputils/_version.py
helputils/core.py
helputils/defaultlog.py
helputils/gfs.py
helputils.egg-info/PKG-INFO
helputils.egg-info/SOURCES.txt
helputils.egg-info/dependency_links.txt
helputils.egg-info/entry_points.txt
helputils.egg-info/requires.txt
helputils.egg-info/top_level.txt