Metadata-Version: 2.1
Name: helputils
Version: 1.4.37
Summary: Bunch of random useful functions and classes
Home-page: https://github.com/eayin2/helputils
Author: eayin2
Author-email: eayin2@gmail.com
License: UNKNOWN
Platform: UNKNOWN
Provides-Extra: sendmails
